msal_extensions/__init__.py
msal_extensions/cache_lock.py
msal_extensions/libsecret.py
msal_extensions/osx.py
msal_extensions/persistence.py
msal_extensions/token_cache.py
msal_extensions/windows.py
msal_extensions-1.2.0.dist-info/LICENSE
msal_extensions-1.2.0.dist-info/METADATA
msal_extensions-1.2.0.dist-info/WHEEL
msal_extensions-1.2.0.dist-info/top_level.txt
msal_extensions-1.2.0.dist-info/RECORD
