Metadata-Version: 2.1
Name: msal-extensions
Version: 1.2.0
Summary: Microsoft Authentication Library extensions (MSAL EX) provides a persistence API that can save your data on disk, encrypted on Windows, macOS and Linux. Concurrent data access will be coordinated by a file lock mechanism.
License: MIT License
Project-URL: Changelog, https://github.com/AzureAD/microsoft-authentication-extensions-for-python/releases
Classifier: License :: OSI Approved :: MIT License
Classifier: Development Status :: 5 - Production/Stable
Classifier: Programming Language :: Python :: 3 :: Only
Classifier: Programming Language :: Python :: 3
Classifier: Programming Language :: Python :: 3.7
Classifier: Programming Language :: Python :: 3.8
Classifier: Programming Language :: Python :: 3.9
Classifier: Programming Language :: Python :: 3.10
Classifier: Programming Language :: Python :: 3.11
Classifier: Programming Language :: Python :: 3.12
Requires-Python: >=3.7
License-File: LICENSE
Requires-Dist: msal<2,>=1.29
Requires-Dist: portalocker<3,>=1.4
